fileinspector/__init__.py
fileinspector/image/ImageInspector.py
fileinspector/image/__init__.py
FileInspector-0.0.1.dist-info/License
FileInspector-0.0.1.dist-info/METADATA
FileInspector-0.0.1.dist-info/WHEEL
FileInspector-0.0.1.dist-info/top_level.txt
FileInspector-0.0.1.dist-info/RECORD
