Metadata-Version: 2.1
Name: FileInspector
Version: 0.0.1
Summary: FileInspector: Python Reusable Application.
Home-page: https://github.com/bhojrampawar/fileinspector
Author: Bhojram pawar
Author-email: bhojrampawar@hotmail.com
License: MIT
Platform: UNKNOWN
Classifier: Intended Audience :: Developers
Classifier: License :: OSI Approved :: MIT License
Classifier: Operating System :: OS Independent
Classifier: Programming Language :: Python
Classifier: Programming Language :: Python :: 3.5
Requires-Dist: pillow
